relatedwidget/__init__.py
relatedwidget/static/relatedwidget/js/relatedwidget.js
relatedwidget/templates/relatedwidget/widget.html
django_relatedadminwidget-0.1.dist-info/METADATA
django_relatedadminwidget-0.1.dist-info/WHEEL
django_relatedadminwidget-0.1.dist-info/top_level.txt
django_relatedadminwidget-0.1.dist-info/RECORD
