Metadata-Version: 2.1
Name: django-relatedadminwidget
Version: 0.1
Summary: Get edit and delete links in your django admin. A utility class to let your model admins inherit from.
Home-page: https://github.com/benjaoming/django-relatedadminwidget
Author: Benjamin Bach
Author-email: benjamin@overtag.dk
License: BSD
Keywords: django admin
Platform: UNKNOWN
Classifier: Development Status :: 4 - Beta
Classifier: Topic :: Utilities
Classifier: License :: OSI Approved :: BSD License
Classifier: Environment :: Web Environment
Classifier: Framework :: Django
Classifier: Intended Audience :: Developers
Classifier: License :: OSI Approved :: BSD License
Classifier: Operating System :: OS Independent
Classifier: Programming Language :: Python
Requires-Dist: Django (>=2.0)
